setup.py
brynq_sdk_ftp/__init__.py
brynq_sdk_ftp/ftps.py
brynq_sdk_ftp/sftp.py
brynq_sdk_ftp.egg-info/PKG-INFO
brynq_sdk_ftp.egg-info/SOURCES.txt
brynq_sdk_ftp.egg-info/dependency_links.txt
brynq_sdk_ftp.egg-info/not-zip-safe
brynq_sdk_ftp.egg-info/requires.txt
brynq_sdk_ftp.egg-info/top_level.txt