Metadata-Version: 1.0
Name: brynq-sdk-ftp
Version: 3.0.3
Summary: FTP wrapper from BrynQ
Home-page: UNKNOWN
Author: BrynQ
Author-email: support@brynq.com
License: BrynQ License
Platform: UNKNOWN
